shipfunk_python/__init__.py
shipfunk_python/shipfunk.py
shipfunk_python-0.1.1.dist-info/AUTHORS.rst
shipfunk_python-0.1.1.dist-info/LICENSE
shipfunk_python-0.1.1.dist-info/METADATA
shipfunk_python-0.1.1.dist-info/WHEEL
shipfunk_python-0.1.1.dist-info/top_level.txt
shipfunk_python-0.1.1.dist-info/RECORD
