Metadata-Version: 2.1
Name: shipfunk-python
Version: 0.1.1
Summary: Python module for Shipfunk API
Home-page: https://github.com/vilkasgroup/shipfunk_python
Author: Jaana Sarajärvi
Author-email: jaana.sarajarvi@vilkas.fi
License: MIT license
Keywords: shipfunk_python,Shipfunk
Platform: UNKNOWN
Classifier: Development Status :: 2 - Pre-Alpha
Classifier: Intended Audience :: Developers
Classifier: License :: OSI Approved :: MIT License
Classifier: Natural Language :: English
Classifier: Programming Language :: Python :: 2.7
Classifier: Programming Language :: Python :: 3.6
Requires-Dist: requests (>=2.7.0)
